Workbook

Sheet Historicals
A1: Financial Item | B1: FY2021 | C1: FY2022 | D1: FY2023 | E1: FY2024 | F1: FY2025
A2: Revenue | B2: 369.5 | C2: 414.8 | D2: 470.8 | E2: 525.7 | F2: 617.5
A3: Cost of Sales | B3: 96.3 | C3: 127.4 | D3: 149.2 | E3: 151.2 | F3: 172.5
A4: Gross Profit | B4: 273.2 | C4: 287.4 | D4: 321.6 | E4: 374.5 | F4: 445
A5: Operating Profit | B5: 151.7 | C5: 157.1 | D5: 170.2 | E5: 201.8 | F5: 261.3
A6: Profit Before Tax | B6: 150.9 | C6: 156.5 | D6: 170.6 | E6: 203 | F6: 262.8
A7: Net Profit | B7: 122 | C7: 128.4 | D7: 134.7 | E7: 151.1 | F7: 196.1
A8: Operating Cash Flow | B8: 132.7 | C8: 121.5 | D8: 192.7 | E8: 196.2 | F8: 247.4
A9: Capital Expenditure | B9: 30 | C9: 32.3 | D9: 28.3 | E9: 32.6 | F9: 40.9
A10: Cash | B10: 85.2 | C10: 71.4 | D10: 90.2 | E10: 107.6 | F10: 132.6
A11: Total Debt | B11: 47 | C11: 48.9 | D11: 49.9 | E11: 47.2 | F11: 45.2
A12: Shares Outstanding | B12: 32.733 | C12: 32.813 | D12: 32.881 | E12: 32.935 | F12: 32.963
A13: EBIT Margin | B13: =B5/B2 -> 0.4105548 | C13: =C5/C2 -> 0.37873674 | D13: =D5/D2 -> 0.36151232 | E13: =E5/E2 -> 0.38386913 | F13: =F5/F2 -> 0.42315789
A14: Unlevered Free Cash Flow (UFCF) | B14: =B8-B9 -> 102.7 | C14: =C8-C9 -> 89.2 | D14: =D8-D9 -> 164.4 | E14: =E8-E9 -> 163.6 | F14: =F8-F9 -> 206.5
A15: Property, Plant & Equipment (PPE) | B15: 49.8 | C15: 55 | D15: 55.7 | E15: 56.5 | F15: 64.9
A16: Working Capital | B16: 99.7 | C16: 109.2 | D16: 125.8 | E16: 133.5 | F16: 163.9

Sheet Forecast
A1: A | B1: B | C1: C
A2: Year | B2: Revenue Growth | C2: Forecast Revenue (£m)
A3: FY2025 (Actual) | B3: — | C3: 617.5
A4: FY2026 | B4: 0.07 | C4: =617.5*1.07 -> 660.725
A5: FY2027 | B5: 0.065 | C5: =C4*1.065 -> 703.67212
A6: FY2028 | B6: 0.06 | C6: =C5*1.06 -> 745.89245
A7: FY2029 | B7: 0.055 | C7: =C6*1.055 -> 786.91654
A8: FY2030 | B8: 0.05 | C8: =C7*1.05 -> 826.26236

Sheet Forecast Assumptions
A1: Year | B1: FY2026 | C1: FY2027 | D1: FY2028 | E1: FY2029 | F1: FY2030
A2: Gross Margin | B2: 0.697 | C2: 0.7 | D2: 0.701 | E2: 0.703 | F2: 0.705
A3: Operating Margin | B3: 0.42 | C3: 0.43 | D3: 0.432 | E3: 0.435 | F3: 0.44
A4: Tax Rate | B4: 0.26 | C4: 0.264 | D4: 0.27 | E4: 0.273 | F4: 0.27
A5: Depreciation (% Revenue) | B5: 0.025 | C5: 0.032 | D5: 0.035 | E5: 0.037 | F5: 0.039
A6: Capex (% Revenue) | B6: 0.065 | C6: 0.067 | D6: 0.0685 | E6: 0.069 | F6: 0.07
A7: Working Capital (% Revenue) | B7: 0.26 | C7: 0.26 | D7: 0.26 | E7: 0.265 | F7: 0.265

Sheet Cash Flow
A1: Item | B1: FY2026 | C1: FY2027 | D1: FY2028 | E1: FY2029 | F1: FY2030
A2: Revenue | B2: =617.5*1.07 -> 660.725 | C2: 703.7 | D2: 745.9 | E2: 786.9 | F2: 826.3
A3: Operating Margain | B3: 0.42 | C3: 0.43 | D3: 0.432 | E3: 0.435 | F3: 0.44
A4: EBIT | B4: =B2*B3 -> 277.5045 | C4: =C2*C3 -> 302.591 | D4: =D2*D3 -> 322.2288 | E4: =E2*E3 -> 342.3015 | F4: =F2*F3 -> 363.572
A5: Tax Rate | B5: 0.26 | C5: 0.264 | D5: 0.27 | E5: 0.273 | F5: 0.27
A6: NOPAT | B6: =B4*(1-B5) -> 205.35333 | C6: =C4*(1-C5) -> 222.70698 | D6: =D4*(1-D5) -> 235.22702 | E6: =E4*(1-E5) -> 248.85319 | F6: =F4*(1-F5) -> 265.40756
A7: Depreciation | B7: =B2*2.5% -> 16.518125 | C7: =C2*3.2% -> 22.5184 | D7: =D2*3.5% -> 26.1065 | E7: =E2*3.7% -> 29.1153 | F7: =F2*3.9% -> 32.2257
A8: Capex | B8: =B2*6.5% -> 42.947125 | C8: =C2*6.7% -> 47.1479 | D8: =D2*6.9% -> 51.4671 | E8: =E2*6.9% -> 54.2961 | F8: =F2*7% -> 57.841
A9: Working Capital | B9: =B2*26% -> 171.7885 | C9: =C2*26% -> 182.962 | D9: =D2*26% -> 193.934 | E9: =E2*26.5% -> 208.5285 | F9: =F2*26.5% -> 218.9695
A10: Change In Working Capital | B10: =B9-163.9 -> 7.8885 | C10: =C9-B9 -> 11.1735 | D10: 10.9 | E10: =E9-D9 -> 14.5945 | F10: 10.5
A11: Unlevered Free Cash Flow (UFCF) | B11: 171.1 | C11: 186.9 | D11: 198.9 | E11: 209.1 | F11: 229.3

Sheet WACC
A1: Item | B1: Value
A2: Risk-Free Rate | B2: 0.0425
A3: Beta | B3: 0.85
A4: Equity Risk Premium | B4: 0.055
A5: Cost of Equity | B5: =B2+B3*B4 -> 0.08925
A6: Cost of Debt | B6: 0.023
A7: Tax Rate | B7: 0.27
A8: Market Value of Equity | B8: 5603.7
A9: Market Value of Debt | B9: 45.2
A10: Equity Weight | B10: 0.992
A11: Debt Weight | B11: 0.008
A12: WACC | B12: 0.0887

Sheet Terminal Value 
A1: Item | B1: Value
A2: Final Year UFCF | B2: 229.3
A3: Terminal Growth Rate | B3: 0.02
A4: WACC | B4: 0.089
A5: Terminal Value | B5: =B2*(1+B3)/(B4-B3) -> 3389.6522

Sheet Discounted Cash Flow
A1: Item | B1: FY2026 | C1: FY2027 | D1: FY2028 | E1: FY2029 | F1: FY2030
A2: UFCF | B2: 171.1 | C2: 186.9 | D2: 198.9 | E2: 209.1 | F2: 229.3
A3: Discount Factor | B3: =1/(1+8.9%)^1 -> 0.91827365 | C3: =1/(1+8.9%)^2 -> 0.84322649 | D3: =1/(1+8.9%)^3 -> 0.77431266 | E3: =1/(1+8.9%)^4 -> 0.71103091 | F3: =1/(1+8.9%)^5 -> 0.65292095
A4: Present Value of UFCF | B4: =171.1*0.9183 -> 157.12113 | C4: =C2*C3 -> 157.59903 | D4: =D2*D3 -> 154.01079 | E4: =E2*E3 -> 148.67656 | F4: =F2*F3 -> 149.71477
A5: Terminal Value | F5: 3389.7
A6: Present Value of Terminal Value | F6: =3389.7*0.6531 -> 2213.8131
A7: Enterprise Value | F7: =SUM(B4:F4)+F6 -> 2980.9354

Sheet Equity Value
A1: Item | B1: Value
A2: Enterprise Value | B2: ='Discounted Cash Flow'!F7 -> 2980.9354
A3: Add: Cash | B3: 132.6
A4: Less: Total Debt | B4: 45.2
A5: Equity Value | B5: =B2+B3-B4 -> 3068.3354
A6: Shares Outstanding (millions) | B6: 33
A7: Intrinsic Value per Share (£) | B7: =B5/B6 -> 92.979859
A8: Current Share Price (£) | B8: 189.4
A9: Upside / (Downside) | B9: =(B7-B8)/B8 -> -0.50908205
A10: Investment View | B10: Overvalued

Sheet Trading Comparables
A1: Company | B1: Enterprise Value | C1: EBITDA | D1: Revenue | E1: EPS | F1: Share Price | G1: EV/Revenue | H1: EV/EBITDA | I1: P/E
A2: Games Workshop | B2: 6110 | C2: 321.5 | D2: 659.7 | E2: 6.23 | F2: 189.3 | G2: =B2/D2 -> 9.2617857 | H2: =B2/C2 -> 19.004666 | I2: =F2/E2 -> 30.385233
A3: Hasbro | B3: 15690 | C3: 1290 | D3: 4970 | E3: 5.6 | F3: 93.52 | G3: =B3/D3 -> 3.1569416 | H3: =B3/C3 -> 12.162791 | I3: =F3/E3 -> 16.7
A4: Mattel | B4: 6450 | C4: 626.59 | D4: 5490 | E4: 1.4 | F4: 14.79 | G4: =B4/D4 -> 1.1748634 | H4: =B4/C4 -> 10.293813 | I4: =F4/E4 -> 10.564286
A5: Funko | B5: 550.44 | C5: 84.76 | D5: 932.64 | E5: -0.04 | F5: 5.88 | G5: =B5/D5 -> 0.59019557 | H5: =B5/C5 -> 6.494101 | I5: N/A
A6: Character Group | B6: 38.31 | C6: 2.66 | D6: 95.73 | E6: -0.1 | F6: 3 | G6: =B6/D6 -> 0.40018803 | H6: =B6/C6 -> 14.402256 | I6: N/A
A7: Median | G7: =MEDIAN(G3:G6) -> 0.88252948 | H7: =MEDIAN(H3:H6) -> 11.228302 | I7: =MEDIAN(I3:I6) -> 13.632143

Sheet Comparable Valuation
A1: A | B1: B
A2: Comparable Valuation
A3: Games Workshop Revenue | B3: 659.7
A4: Games Workshop EBITDA | B4: 321.5
A5: Games Workshop EPS | B5: 6.23
A6: Cash | B6: 132.6
A7: Total Debt | B7: 45.2
A8: Shares Outstanding (m) | B8: 33
A10: EV/Revenue Valuation
A11: Median EV/Revenue | B11: ='Trading Comparables'!G7 -> 0.88252948
A12: Implied Enterprise Value | B12: =B3*B11 -> 582.2047
A13: Add: Cash | B13: =B6 -> 132.6
A14: Less: Total Debt | B14: =B7 -> 45.2
A15: Implied Equity Value | B15: =B12+B13-B14 -> 669.6047
A16: Implied Share Price | B16: =B15/B8 -> 20.291051
A18: EV/EBITDA Valuation
A19: Median EV/EBITDA | B19: 12.16
A20: Implied Enterprise Value | B20: 3910.34
A21: Add: Cash | B21: =B6 -> 132.6
A22: Less: Total Debt | B22: =B7 -> 45.2
A23: Implied Equity Value | B23: =B20+B21-B22 -> 3997.74
A24: Implied Share Price | B24: =B23/B8 -> 121.14364
A26: P/E Valuation
A27: Median P/E | B27: 16.7
A28: Implied Equity Value | B28: =B5*B27*B8 -> 3433.353
A29: Implied Share Price | B29: =B28/B8 -> 104.041

Sheet Sensitivity Analysis
A1: Sensitivity Analysis — Implied Share Price (£)
A3: WACC / Terminal Growth | B3: 0.01 | C3: 0.015 | D3: 0.02 | E3: 0.025 | F3: 0.03
A4: 0.07 | B4: {=(SUMPRODUCT('Discounted Cash Flow'!$B$2:$F$2,1/(1+$A4)^{1,2,3,4,5})+('Discounted Cash Flow'!$F$2*(1+B$3)/($A4-B$3))/(1+$A4)^5+'Equity Value'!$B$3-'Equity Value'!$B$4)/'Equity Value'!$B$6} -> 110.54444 | C4: {=(SUMPRODUCT('Discounted Cash Flow'!$B$2:$F$2,1/(1+$A4)^{1,2,3,4,5})+('Discounted Cash Flow'!$F$2*(1+C$3)/($A4-C$3))/(1+$A4)^5+'Equity Value'!$B$3-'Equity Value'!$B$4)/'Equity Value'!$B$6} -> 118.57621 | D4: {=(SUMPRODUCT('Discounted Cash Flow'!$B$2:$F$2,1/(1+$A4)^{1,2,3,4,5})+('Discounted Cash Flow'!$F$2*(1+D$3)/($A4-D$3))/(1+$A4)^5+'Equity Value'!$B$3-'Equity Value'!$B$4)/'Equity Value'!$B$6} -> 128.21432 | E4: {=(SUMPRODUCT('Discounted Cash Flow'!$B$2:$F$2,1/(1+$A4)^{1,2,3,4,5})+('Discounted Cash Flow'!$F$2*(1+E$3)/($A4-E$3))/(1+$A4)^5+'Equity Value'!$B$3-'Equity Value'!$B$4)/'Equity Value'!$B$6} -> 139.99425 | F4: {=(SUMPRODUCT('Discounted Cash Flow'!$B$2:$F$2,1/(1+$A4)^{1,2,3,4,5})+('Discounted Cash Flow'!$F$2*(1+F$3)/($A4-F$3))/(1+$A4)^5+'Equity Value'!$B$3-'Equity Value'!$B$4)/'Equity Value'!$B$6} -> 154.71915
A5: 0.075 | B5: {=(SUMPRODUCT('Discounted Cash Flow'!$B$2:$F$2,1/(1+$A5)^{1,2,3,4,5})+('Discounted Cash Flow'!$F$2*(1+B$3)/($A5-B$3))/(1+$A5)^5+'Equity Value'!$B$3-'Equity Value'!$B$4)/'Equity Value'!$B$6} -> 102.01552 | C5: {=(SUMPRODUCT('Discounted Cash Flow'!$B$2:$F$2,1/(1+$A5)^{1,2,3,4,5})+('Discounted Cash Flow'!$F$2*(1+C$3)/($A5-C$3))/(1+$A5)^5+'Equity Value'!$B$3-'Equity Value'!$B$4)/'Equity Value'!$B$6} -> 108.68607 | D5: {=(SUMPRODUCT('Discounted Cash Flow'!$B$2:$F$2,1/(1+$A5)^{1,2,3,4,5})+('Discounted Cash Flow'!$F$2*(1+D$3)/($A5-D$3))/(1+$A5)^5+'Equity Value'!$B$3-'Equity Value'!$B$4)/'Equity Value'!$B$6} -> 116.56945 | E5: {=(SUMPRODUCT('Discounted Cash Flow'!$B$2:$F$2,1/(1+$A5)^{1,2,3,4,5})+('Discounted Cash Flow'!$F$2*(1+E$3)/($A5-E$3))/(1+$A5)^5+'Equity Value'!$B$3-'Equity Value'!$B$4)/'Equity Value'!$B$6} -> 126.0295 | F5: {=(SUMPRODUCT('Discounted Cash Flow'!$B$2:$F$2,1/(1+$A5)^{1,2,3,4,5})+('Discounted Cash Flow'!$F$2*(1+F$3)/($A5-F$3))/(1+$A5)^5+'Equity Value'!$B$3-'Equity Value'!$B$4)/'Equity Value'!$B$6} -> 137.59179
A6: 0.08 | B6: {=(SUMPRODUCT('Discounted Cash Flow'!$B$2:$F$2,1/(1+$A6)^{1,2,3,4,5})+('Discounted Cash Flow'!$F$2*(1+B$3)/($A6-B$3))/(1+$A6)^5+'Equity Value'!$B$3-'Equity Value'!$B$4)/'Equity Value'!$B$6} -> 94.70904 | C6: {=(SUMPRODUCT('Discounted Cash Flow'!$B$2:$F$2,1/(1+$A6)^{1,2,3,4,5})+('Discounted Cash Flow'!$F$2*(1+C$3)/($A6-C$3))/(1+$A6)^5+'Equity Value'!$B$3-'Equity Value'!$B$4)/'Equity Value'!$B$6} -> 100.32151 | D6: {=(SUMPRODUCT('Discounted Cash Flow'!$B$2:$F$2,1/(1+$A6)^{1,2,3,4,5})+('Discounted Cash Flow'!$F$2*(1+D$3)/($A6-D$3))/(1+$A6)^5+'Equity Value'!$B$3-'Equity Value'!$B$4)/'Equity Value'!$B$6} -> 106.86938 | E6: {=(SUMPRODUCT('Discounted Cash Flow'!$B$2:$F$2,1/(1+$A6)^{1,2,3,4,5})+('Discounted Cash Flow'!$F$2*(1+E$3)/($A6-E$3))/(1+$A6)^5+'Equity Value'!$B$3-'Equity Value'!$B$4)/'Equity Value'!$B$6} -> 114.60778 | F6: {=(SUMPRODUCT('Discounted Cash Flow'!$B$2:$F$2,1/(1+$A6)^{1,2,3,4,5})+('Discounted Cash Flow'!$F$2*(1+F$3)/($A6-F$3))/(1+$A6)^5+'Equity Value'!$B$3-'Equity Value'!$B$4)/'Equity Value'!$B$6} -> 123.89386
A7: 0.085 | B7: {=(SUMPRODUCT('Discounted Cash Flow'!$B$2:$F$2,1/(1+$A7)^{1,2,3,4,5})+('Discounted Cash Flow'!$F$2*(1+B$3)/($A7-B$3))/(1+$A7)^5+'Equity Value'!$B$3-'Equity Value'!$B$4)/'Equity Value'!$B$6} -> 88.380417 | C7: {=(SUMPRODUCT('Discounted Cash Flow'!$B$2:$F$2,1/(1+$A7)^{1,2,3,4,5})+('Discounted Cash Flow'!$F$2*(1+C$3)/($A7-C$3))/(1+$A7)^5+'Equity Value'!$B$3-'Equity Value'!$B$4)/'Equity Value'!$B$6} -> 93.15551 | D7: {=(SUMPRODUCT('Discounted Cash Flow'!$B$2:$F$2,1/(1+$A7)^{1,2,3,4,5})+('Discounted Cash Flow'!$F$2*(1+D$3)/($A7-D$3))/(1+$A7)^5+'Equity Value'!$B$3-'Equity Value'!$B$4)/'Equity Value'!$B$6} -> 98.665233 | E7: {=(SUMPRODUCT('Discounted Cash Flow'!$B$2:$F$2,1/(1+$A7)^{1,2,3,4,5})+('Discounted Cash Flow'!$F$2*(1+E$3)/($A7-E$3))/(1+$A7)^5+'Equity Value'!$B$3-'Equity Value'!$B$4)/'Equity Value'!$B$6} -> 105.09324 | F7: {=(SUMPRODUCT('Discounted Cash Flow'!$B$2:$F$2,1/(1+$A7)^{1,2,3,4,5})+('Discounted Cash Flow'!$F$2*(1+F$3)/($A7-F$3))/(1+$A7)^5+'Equity Value'!$B$3-'Equity Value'!$B$4)/'Equity Value'!$B$6} -> 112.68998
A8: 0.09 | B8: {=(SUMPRODUCT('Discounted Cash Flow'!$B$2:$F$2,1/(1+$A8)^{1,2,3,4,5})+('Discounted Cash Flow'!$F$2*(1+B$3)/($A8-B$3))/(1+$A8)^5+'Equity Value'!$B$3-'Equity Value'!$B$4)/'Equity Value'!$B$6} -> 82.846219 | C8: {=(SUMPRODUCT('Discounted Cash Flow'!$B$2:$F$2,1/(1+$A8)^{1,2,3,4,5})+('Discounted Cash Flow'!$F$2*(1+C$3)/($A8-C$3))/(1+$A8)^5+'Equity Value'!$B$3-'Equity Value'!$B$4)/'Equity Value'!$B$6} -> 86.948287 | D8: {=(SUMPRODUCT('Discounted Cash Flow'!$B$2:$F$2,1/(1+$A8)^{1,2,3,4,5})+('Discounted Cash Flow'!$F$2*(1+D$3)/($A8-D$3))/(1+$A8)^5+'Equity Value'!$B$3-'Equity Value'!$B$4)/'Equity Value'!$B$6} -> 91.636365 | E8: {=(SUMPRODUCT('Discounted Cash Flow'!$B$2:$F$2,1/(1+$A8)^{1,2,3,4,5})+('Discounted Cash Flow'!$F$2*(1+E$3)/($A8-E$3))/(1+$A8)^5+'Equity Value'!$B$3-'Equity Value'!$B$4)/'Equity Value'!$B$6} -> 97.045686 | F8: {=(SUMPRODUCT('Discounted Cash Flow'!$B$2:$F$2,1/(1+$A8)^{1,2,3,4,5})+('Discounted Cash Flow'!$F$2*(1+F$3)/($A8-F$3))/(1+$A8)^5+'Equity Value'!$B$3-'Equity Value'!$B$4)/'Equity Value'!$B$6} -> 103.35656

Sheet Football Field
A1: Valuation Method | B1: Low (£) | C1: High (£) | D1: Range | F1: Current Price Line | G1: 189.4
A2: DCF | B2: 82.85 | C2: 154.72 | D2: =C2-B2 -> 71.87 | F2: DCF | G2: 189.4
A3: EV/Revenue | B3: 10.64 | C3: 65.82 | D3: =C3-B3 -> 55.18 | F3: EV/Revenue | G3: 189.4
A4: EV/EBITDA | B4: 65.88 | C4: 142.94 | D4: =C4-B4 -> 77.06 | F4: EV/EBITDA | G4: 189.4
A5: P/E | B5: =6.23*10.56 -> 65.7888 | C5: =6.23*16.7 -> 104.041 | D5: =C5-B5 -> 38.2522
A6: Current Share Price | B6: 189.4 | C6: 189.4
